ursa_sync/__init__.py
ursa_sync-0.0.1.dist-info/METADATA
ursa_sync-0.0.1.dist-info/WHEEL
ursa_sync-0.0.1.dist-info/RECORD
